al360_trustworthyai_vision/__init__.py
al360_trustworthyai_vision/version.py
al360_trustworthyai_vision/common/__init__.py
al360_trustworthyai_vision/common/constants.py
al360_trustworthyai_vision/common/interfaces.py
al360_trustworthyai_vision/managers/__init__.py
al360_trustworthyai_vision/managers/error_analysis_manager.py
al360_trustworthyai_vision/managers/explainer_manager.py
al360_trustworthyai_vision/rai_vision_insights/__init__.py
al360_trustworthyai_vision/rai_vision_insights/rai_vision_insights.py
al360_trustworthyai_vision/utils/__init__.py
al360_trustworthyai_vision/utils/feature_extractors.py
al360_trustworthyai_vision/utils/image_reader.py
al360_trustworthyai_vision/utils/image_utils.py
al360_trustworthyai_vision-0.3.8.dist-info/METADATA
al360_trustworthyai_vision-0.3.8.dist-info/WHEEL
al360_trustworthyai_vision-0.3.8.dist-info/top_level.txt
al360_trustworthyai_vision-0.3.8.dist-info/RECORD
